rtl/sync_fifo.v
`timescale 1ns / 1ps
module sync_fifo (clk,rst,wr_en,rd_en,data_in,data_out,full,empty);
input  wire clk;
input  wire rst;
input  wire wr_en;
input  wire rd_en;
input  wire [7:0]  data_in;
output reg  [7:0]  data_out;
output wire full;
output wire empty;

parameter DEPTH = 16;
parameter WIDTH = 8;

localparam ADDR_W = $clog2(DEPTH);

reg [WIDTH-1:0] mem [0:DEPTH-1];
reg [ADDR_W-1:0] wr_ptr, rd_ptr;
reg [ADDR_W:0]   count;

always @(posedge clk) begin
if (rst) begin
    wr_ptr   <= 0;
    rd_ptr   <= 0;
    count    <= 0;
    data_out <= 0;
    end 
else begin
case ({wr_en && !full, rd_en && !empty})

2'b10: begin
    mem[wr_ptr] <= data_in;
    wr_ptr <= wr_ptr + 1;
    count <= count + 1;
end

2'b01: begin
    data_out <= mem[rd_ptr];
    rd_ptr <= rd_ptr + 1;
    count <= count - 1;
end

2'b11: begin
    mem[wr_ptr] <= data_in;
    data_out <= mem[rd_ptr];
    wr_ptr <= wr_ptr + 1;
    rd_ptr <= rd_ptr + 1;
end

default: begin
    wr_ptr   <= wr_ptr;
    rd_ptr   <= rd_ptr;
    count    <= count;
    data_out <= data_out;
end

endcase
end
end

assign empty = (count == 0);
assign full  = (count == DEPTH);

endmodule

test.v
`timescale 1ns / 1ps

module tb_sync_fifo;

    // Testbench signals
    reg         clk;
    reg         rst;
    reg         wr_en;
    reg         rd_en;
    reg  [7:0]  data_in;
    
    wire [7:0]  data_out;
    wire        full;
    wire        empty;

    // DUT instantiation
    sync_fifo #(
        .DEPTH(16),
        .WIDTH(8)
    ) dut (
        .clk     (clk),
        .rst     (rst),
        .wr_en   (wr_en),
        .rd_en   (rd_en),
        .data_in (data_in),
        .data_out(data_out),
        .full    (full),
        .empty   (empty)
    );

    // Clock generation: 100 MHz
    initial begin
        clk = 0;
        forever #5 clk = ~clk;
    end

    // Test stimulus
    initial begin
        // Initialize
        rst      = 1;
        wr_en    = 0;
        rd_en    = 0;
        data_in  = 8'h00;

        $dumpfile("sync_fifo_tb.vcd");
        $dumpvars(1, tb_sync_fifo);

        // Reset
        #20;
        rst = 0;
        #20;

        $display("\n=== TEST 1: Fill to FULL ===");
        repeat(16) begin
            @(posedge clk);
            wr_en   = 1;
            rd_en   = 0;
            data_in = data_in + 8'h11;   // 00,11,22,33,...
            #1; // small delay to let signals settle for display
            $display("t=%5t | wr=%b rd=%b | din=%h | full=%b empty=%b | count should be %0d",
                     $time, wr_en, rd_en, data_in, full, empty, dut.count);
        end

        @(posedge clk);
        wr_en = 0;
        #20;

        $display("\n=== TEST 2: Try write when FULL (should be ignored) ===");
        @(posedge clk);
        wr_en   = 1;
        data_in = 8'hFF;
        #20;
        wr_en = 0;

        $display("\n=== TEST 3: Read everything until EMPTY ===");
        repeat(16) begin
            @(posedge clk);
            wr_en   = 0;
            rd_en   = 1;
            #1;
            $display("t=%5t | wr=%b rd=%b | dout=%h | full=%b empty=%b | count should be %0d",
                     $time, wr_en, rd_en, data_out, full, empty, dut.count);
        end

        @(posedge clk);
        rd_en = 0;
        #20;

        $display("\n=== TEST 4: Try read when EMPTY (should keep old value) ===");
        @(posedge clk);
        rd_en = 1;
        #20;
        rd_en = 0;

        $display("\n=== TEST 5: Simultaneous read & write (should maintain count) ===");
        // First put some data
        repeat(5) begin
            @(posedge clk);
            wr_en   = 1;
            rd_en   = 0;
            data_in = $random;
        end
        wr_en = 0; rd_en = 0; #20;

        // Now simultaneous r/w for 8 cycles
        $display("Starting simultaneous read+write...");
        repeat(8) begin
            @(posedge clk);
            wr_en   = 1;
            rd_en   = 1;
            data_in = $random;
            #1;
            $display("t=%5t | wr=%b rd=%b | din=%h dout=%h | full=%b empty=%b | count=%0d",
                     $time, wr_en, rd_en, data_in, data_out, full, empty, dut.count);
        end
        wr_en = 0; rd_en = 0; #20;

        $display("\n=== TEST 6: Random read/write pattern ===");
        repeat(40) begin
            @(posedge clk);
            {wr_en, rd_en} = $random;
            
            // Prevent illegal: don't write when full, don't read when empty
            if (full)  wr_en = 0;
            if (empty) rd_en = 0;
            
            if (wr_en) data_in = $random;
            
            #1;
            if (wr_en || rd_en)
                $display("t=%5t | wr=%b rd=%b | din=%h dout=%h | full=%b empty=%b count=%0d ptr_wr=%0d ptr_rd=%0d",
                         $time, wr_en, rd_en, data_in, data_out, full, empty, dut.count, dut.wr_ptr, dut.rd_ptr);
        end

        #100;
        $display("\nSimulation finished.");
        $finish;
    end

    // Optional: more readable monitoring
    initial begin
        $monitor("t=%5t  wr=%b rd=%b  full=%b empty=%b  count=%2d  wptr=%2d rptr=%2d  din=%h dout=%h",
                 $time, wr_en, rd_en, full, empty, dut.count, dut.wr_ptr, dut.rd_ptr, data_in, data_out);
    end

endmodule

results/sync_fifo_tb.vcd
$date
	Tue Jun 30 11:51:09 2026
$end
$version
	Icarus Verilog
$end
$timescale
	1ps
$end
$scope module tb_sync_fifo $end
$var wire 1 ! full $end
$var wire 1 " empty $end
$var wire 8 # data_out [7:0] $end
$var reg 1 $ clk $end
$var reg 8 % data_in [7:0] $end
$var reg 1 & rd_en $end
$var reg 1 ' rst $end
$var reg 1 ( wr_en $end
$upscope $end
$enddefinitions $end
$comment Show the parameter values. $end
$dumpall
$end
#0
$dumpvars
0(
1'
0&
b0 %
0$
bx #
x"
x!
$end
#5000
b0 #
1"
0!
1$
#10000
0$
#15000
1$
#20000
0$
0'
#25000
1$
#30000
0$
#35000
1$
#40000
0$
#45000
0"
b10001 %
1(
1$
#50000
0$
#55000
b100010 %
1$
#60000
0$
#65000
b110011 %
1$
#70000
0$
#75000
b1000100 %
1$
#80000
0$
#85000
b1010101 %
1$
#90000
0$
#95000
b1100110 %
1$
#100000
0$
#105000
b1110111 %
1$
#110000
0$
#115000
b10001000 %
1$
#120000
0$
#125000
b10011001 %
1$
#130000
0$
#135000
b10101010 %
1$
#140000
0$
#145000
b10111011 %
1$
#150000
0$
#155000
b11001100 %
1$
#160000
0$
#165000
b11011101 %
1$
#170000
0$
#175000
b11101110 %
1$
#180000
0$
#185000
b11111111 %
1$
#190000
0$
#195000
1!
b10000 %
1$
#200000
0$
#205000
0(
1$
#210000
0$
#215000
1$
#220000
0$
#225000
b11111111 %
1(
1$
#230000
0$
#235000
1$
#240000
0$
#245000
0!
b10001 #
1&
1$
0(
#250000
0$
#255000
b100010 #
1$
#260000
0$
#265000
b110011 #
1$
#270000
0$
#275000
b1000100 #
1$
#280000
0$
#285000
b1010101 #
1$
#290000
0$
#295000
b1100110 #
1$
#300000
0$
#305000
b1110111 #
1$
#310000
0$
#315000
b10001000 #
1$
#320000
0$
#325000
b10011001 #
1$
#330000
0$
#335000
b10101010 #
1$
#340000
0$
#345000
b10111011 #
1$
#350000
0$
#355000
b11001100 #
1$
#360000
0$
#365000
b11011101 #
1$
#370000
0$
#375000
b11101110 #
1$
#380000
0$
#385000
b11111111 #
1$
#390000
0$
#395000
1"
b10000 #
1$
#400000
0$
#405000
0&
1$
#410000
0$
#415000
1$
#420000
0$
#425000
1&
1$
#430000
0$
#435000
1$
#440000
0$
#445000
0"
b100100 %
1(
1$
0&
#450000
0$
#455000
b10000001 %
1$
#460000
0$
#465000
b1001 %
1$
#470000
0$
#475000
b1100011 %
1$
#480000
0$
#485000
0(
b1101 %
1$
#490000
0$
#495000
1$
#500000
0$
#505000
b100100 #
b10001101 %
1&
1(
1$
#510000
0$
#515000
b1100101 %
1$
#520000
0$
#525000
b1001 #
b10010 %
1$
#530000
0$
#535000
b1 %
1$
#540000
0$
#545000
b10001101 #
b1101 %
1$
#550000
0$
#555000
b1100101 #
b1110110 %
1$
#560000
0$
#565000
b10010 #
b111101 %
1$
#570000
0$
#575000
b1 #
b11101101 %
1$
#576000
0&
0(
#580000
0$
#585000
1$
#590000
0$
#595000
1$
#600000
0$
#605000
1$
#610000
0$
#615000
b1101 #
1&
1$
#620000
0$
#625000
b11000101 %
1(
0&
1$
#630000
0$
#635000
b11100101 %
1$
#640000
0$
#645000
b1110110 #
b10010 %
1&
1$
#650000
0$
#655000
b111101 #
b11110010 %
1$
#660000
0$
#665000
b11101000 %
0&
1$
#670000
0$
#675000
b11101101 #
0(
1&
1$
#680000
0$
#685000
0&
1$
#690000
0$
#695000
b11000101 #
1&
1$
#700000
0$
#705000
b11100101 #
1$
#710000
0$
#715000
b10010 #
1$
#720000
0$
#725000
b11110010 #
b1010 %
1(
1$
#730000
0$
#735000
0(
0&
1$
#740000
0$
#745000
1$
#750000
0$
#755000
b10011101 %
1(
1$
#760000
0$
#765000
b10011 %
1$
#770000
0$
#775000
b11101000 #
0(
1&
1$
#780000
0$
#785000
b1010 #
b1101011 %
1(
1$
#790000
0$
#795000
b10011101 #
0(
1$
#800000
0$
#805000
b10101110 %
1(
0&
1$
#810000
0$
#815000
b10011 #
0(
1&
1$
#820000
0$
#825000
b1101011 #
b100011 %
1(
1$
#830000
0$
#835000
b11001010 %
0&
1$
#840000
0$
#845000
0(
1$
#850000
0$
#855000
b10001010 %
1(
1$
#860000
0$
#865000
b10101110 #
0(
1&
1$
#870000
0$
#875000
0&
1$
#880000
0$
#885000
1$
#890000
0$
#895000
b100011 #
1&
1$
#900000
0$
#905000
b11001010 #
b10110110 %
1(
1$
#910000
0$
#915000
b10101110 %
0&
1$
#920000
0$
#925000
0(
1$
#930000
0$
#935000
b1011 %
1(
1$
#940000
0$
#945000
b10001010 #
0(
1&
1$
#950000
0$
#955000
b10110110 #
1$
#960000
0$
#965000
b10101110 #
b111011 %
1(
1$
#970000
0$
#975000
b1111110 %
0&
1$
#980000
0$
#985000
b1011 #
0(
1&
1$
#990000
0$
#995000
b111011 #
1$
#1000000
0$
#1005000
1"
b1111110 #
1$
